{
  "trend_analysis": {
    "trend": "NEUTRAL",
    "confidence": "LOW",
    "ma_alignment": "bearish",
    "price_action": "bearish",
    "momentum": "bullish",
    "rsi": 44.279273790666586,
    "macd_signal": "bullish"
  },
  "support_resistance": {
    "current_price": 2099.57,
    "resistance": [
      2147.1342857142854,
      2197.01,
      2329.5280000000002
    ],
    "support": [
      2083.565,
      2001.74,
      1914.69
    ],
    "nearest_resistance": 2147.1342857142854,
    "nearest_support": 2083.565
  },
  "trading_signal": {
    "signal": "WAIT",
    "action": "WAIT - No clear entry signal",
    "confidence": "LOW",
    "scores": {
      "buy": 4,
      "sell": 0,
      "short": 0
    },
    "trend_context": "NEUTRAL",
    "entry": 2083.56,
    "stop_loss": 2021.06,
    "target": 2147.13,
    "risk_reward": 1.02,
    "reasoning": "Market trend: NEUTRAL. RSI neutral at 44.3. MACD bullish crossover. Support at $2083.57 (0.8% below). Resistance at $2147.13 (2.3% above)\n\nYou are currently OUT OF TRADE. No clear entry opportunity. Wait for a better setup.",
    "user_context": {
      "trade_status": "OUT_OF_TRADE",
      "position": {
        "entry_price": 0,
        "position_size": 0,
        "entry_time": null,
        "type": "LONG"
      },
      "last_updated": null,
      "notes": "Set trade_status to IN_TRADE when you enter a position, OUT_OF_TRADE when you exit"
    },
    "derivatives_data": {
      "funding_rate": 7.9955966992e-05,
      "open_interest": 15545056008.48574,
      "long_short_ratio": null,
      "fear_greed_index": 25,
      "fear_greed_classification": "Extreme Fear"
    }
  },
  "market_filters": {
    "trend": "down",
    "trend_strength": 1.0,
    "ma_200": 2264.94595,
    "near_sr": true,
    "sr_levels": [
      2320.7126,
      2054.1034,
      2126.8149999999996,
      1981.3917999999999,
      2926.6426
    ]
  },
  "derivatives_context": {
    "funding_rate": 7.9955966992e-05,
    "open_interest": 15546690870.309044,
    "long_short_ratio": null,
    "fear_greed_index": 25,
    "fear_greed_classification": "Extreme Fear"
  },
  "defi_signals": {
    "uniswap_v3": {
      "optimal_range_1sigma": [
        2071.76,
        2127.38
      ],
      "optimal_range_2sigma": [
        2043.95,
        2155.19
      ],
      "projected_fee_apy": null,
      "il_at_10pct": 0.113,
      "il_at_20pct": 0.414,
      "il_at_30pct": 0.854,
      "tvl_usd": 0,
      "fees_24h_usd": 0,
      "recommendation": "WAIT"
    },
    "sushiswap": {
      "tvl_usd": null,
      "volume_24h_usd": null,
      "fees_24h_usd": null
    },
    "protocol_comparison": {
      "uniswap_v3_apy": 0,
      "sushiswap_apy": null,
      "better_protocol": "UNISWAP_V3",
      "better_apy": 0
    },
    "fear_greed_value": 25,
    "fear_greed_label": "Extreme Fear",
    "gas_gwei": null,
    "gas_label": "LOW",
    "onchain_momentum": "NEUTRAL"
  },
  "onchain_context": {
    "gas": {
      "safe_gas_gwei": null,
      "propose_gas_gwei": null,
      "fast_gas_gwei": null,
      "label": "LOW"
    },
    "uniswap_v3_pool": {
      "token0_price": null,
      "token1_price": null,
      "liquidity": null,
      "tick": null,
      "tvl_usd": null,
      "volume_24h_usd": null,
      "fees_24h_usd": null,
      "hour_data": []
    },
    "fear_greed": {
      "value": 25,
      "label": "Extreme Fear",
      "history": [
        {
          "value": 25,
          "label": "Extreme Fear"
        },
        {
          "value": 28,
          "label": "Fear"
        },
        {
          "value": 28,
          "label": "Fear"
        },
        {
          "value": 29,
          "label": "Fear"
        },
        {
          "value": 27,
          "label": "Fear"
        },
        {
          "value": 25,
          "label": "Extreme Fear"
        },
        {
          "value": 28,
          "label": "Fear"
        }
      ]
    },
    "eth_supply": {
      "eth_burned_all_time": null,
      "supply_change": null
    },
    "onchain_momentum": "NEUTRAL",
    "fetched_at": "2026-05-24T16:28:56.538327Z"
  },
  "signal_score": {
    "score": 65,
    "signal": "WAIT",
    "confidence": "LOW",
    "obv_trend": "UP",
    "stoch_rsi": 0.893,
    "vwap": 2097.78,
    "rsi_divergence": "NONE"
  },
  "kelly": {
    "kelly_fraction": 0.25,
    "kelly_pct": 25.0,
    "win_rate": 0.55,
    "win_loss_ratio": 1.5
  },
  "generated_at": "2026-05-24T16:28:56.840284+00:00"
}