{
  "timestamp": "2026-05-06T15:53:49.492045+00:00",
  "current_price": 2359.16,
  "predictions": {
    "15min": {
      "timestamp": "2026-05-06T16:08:49.492045+00:00",
      "price": 2381.126146239452,
      "change_pct": 0.9582746097434514,
      "confidence_band": 14.0,
      "models": {
        "linear": 2357.8723719171917,
        "polynomial": 2353.1932545391874,
        "random_forest": 2360.0893699011594,
        "boosted": 2388.877404346872
      },
      "boosted_metrics": {
        "rmse": 7.2925,
        "directional_accuracy": 53.85,
        "train_size": 487,
        "test_size": 105,
        "models": [
          "lgb",
          "xgb"
        ],
        "feature_importance": {
          "close": 415.0,
          "volume": 59.0,
          "RSI": 72.0,
          "MACD": 94.0,
          "bb_position": 62.0,
          "obv": 159.0,
          "stoch_rsi": 50.0,
          "vwap_distance": 50.0,
          "atr_14": 83.0,
          "gas_price": 0.0,
          "fear_greed": 0.0
        }
      },
      "weights": {
        "lightgbm_xgboost": 0.75,
        "linear": 0.25,
        "polynomial": 0.0,
        "ml_features": 0.0
      },
      "weight_source": "boosted_ensemble"
    },
    "30min": {
      "timestamp": "2026-05-06T16:23:49.492045+00:00",
      "price": 2380.9115283276606,
      "change_pct": 0.949174943138634,
      "confidence_band": 14.99,
      "models": {
        "linear": 2357.013900270027,
        "polynomial": 2349.296942935158,
        "random_forest": 2360.0893699011594,
        "boosted": 2388.877404346872
      },
      "boosted_metrics": {
        "rmse": 7.2925,
        "directional_accuracy": 53.85,
        "train_size": 487,
        "test_size": 105,
        "models": [
          "lgb",
          "xgb"
        ],
        "feature_importance": {
          "close": 415.0,
          "volume": 59.0,
          "RSI": 72.0,
          "MACD": 94.0,
          "bb_position": 62.0,
          "obv": 159.0,
          "stoch_rsi": 50.0,
          "vwap_distance": 50.0,
          "atr_14": 83.0,
          "gas_price": 0.0,
          "fear_greed": 0.0
        }
      },
      "weights": {
        "lightgbm_xgboost": 0.75,
        "linear": 0.25,
        "polynomial": 0.0,
        "ml_features": 0.0
      },
      "weight_source": "boosted_ensemble"
    },
    "60min": {
      "timestamp": "2026-05-06T16:53:49.492045+00:00",
      "price": 2380.4822925040785,
      "change_pct": 0.930975609929019,
      "confidence_band": 17.81,
      "models": {
        "linear": 2355.2969569756974,
        "polynomial": 2339.605669754058,
        "random_forest": 2360.0893699011594,
        "boosted": 2388.877404346872
      },
      "boosted_metrics": {
        "rmse": 7.2925,
        "directional_accuracy": 53.85,
        "train_size": 487,
        "test_size": 105,
        "models": [
          "lgb",
          "xgb"
        ],
        "feature_importance": {
          "close": 415.0,
          "volume": 59.0,
          "RSI": 72.0,
          "MACD": 94.0,
          "bb_position": 62.0,
          "obv": 159.0,
          "stoch_rsi": 50.0,
          "vwap_distance": 50.0,
          "atr_14": 83.0,
          "gas_price": 0.0,
          "fear_greed": 0.0
        }
      },
      "weights": {
        "lightgbm_xgboost": 0.75,
        "linear": 0.25,
        "polynomial": 0.0,
        "ml_features": 0.0
      },
      "weight_source": "boosted_ensemble"
    },
    "120min": {
      "timestamp": "2026-05-06T17:53:49.492045+00:00",
      "price": 2379.623820856914,
      "change_pct": 0.8945769435097694,
      "confidence_band": 27.24,
      "models": {
        "linear": 2351.8630703870385,
        "polynomial": 2312.6285234996967,
        "random_forest": 2360.0893699011594,
        "boosted": 2388.877404346872
      },
      "boosted_metrics": {
        "rmse": 7.2925,
        "directional_accuracy": 53.85,
        "train_size": 487,
        "test_size": 105,
        "models": [
          "lgb",
          "xgb"
        ],
        "feature_importance": {
          "close": 415.0,
          "volume": 59.0,
          "RSI": 72.0,
          "MACD": 94.0,
          "bb_position": 62.0,
          "obv": 159.0,
          "stoch_rsi": 50.0,
          "vwap_distance": 50.0,
          "atr_14": 83.0,
          "gas_price": 0.0,
          "fear_greed": 0.0
        }
      },
      "weights": {
        "lightgbm_xgboost": 0.75,
        "linear": 0.25,
        "polynomial": 0.0,
        "ml_features": 0.0
      },
      "weight_source": "boosted_ensemble"
    }
  },
  "market_condition": null,
  "rl_enabled": false,
  "accuracy_summary": null,
  "onchain_data": {
    "gas": {
      "safe_gas_gwei": null,
      "propose_gas_gwei": null,
      "fast_gas_gwei": null,
      "label": "LOW"
    },
    "uniswap_v3_pool": {
      "token0_price": null,
      "token1_price": null,
      "liquidity": null,
      "tick": null,
      "tvl_usd": null,
      "volume_24h_usd": null,
      "fees_24h_usd": null,
      "hour_data": []
    },
    "fear_greed": {
      "value": 46,
      "label": "Fear",
      "history": [
        {
          "value": 46,
          "label": "Fear"
        },
        {
          "value": 50,
          "label": "Neutral"
        },
        {
          "value": 40,
          "label": "Fear"
        },
        {
          "value": 47,
          "label": "Neutral"
        },
        {
          "value": 39,
          "label": "Fear"
        },
        {
          "value": 26,
          "label": "Fear"
        },
        {
          "value": 29,
          "label": "Fear"
        }
      ]
    },
    "eth_supply": {
      "eth_burned_all_time": null,
      "supply_change": null
    },
    "onchain_momentum": "NEUTRAL",
    "fetched_at": "2026-05-06T15:53:49.492010Z"
  },
  "model_scores": {
    "linear": 0.5,
    "polynomial": 0.7,
    "ml_features": 0.9
  },
  "model_weights": {
    "linear": 0.25,
    "polynomial": 0.35,
    "ml_features": 0.4
  },
  "trend_analysis": {
    "trend": "NEUTRAL",
    "rsi": 50.0,
    "rsi_signal": "NEUTRAL",
    "macd": 0.0,
    "macd_signal": "NEUTRAL",
    "bb_position": "MIDDLE",
    "current_price": 2359.16,
    "sma_20": 2359.16,
    "bb_upper": 2406.3432,
    "bb_lower": 2311.9768
  }
}