{
  "timestamp": "2026-04-15T05:04:30.888420+00:00",
  "current_price": 2336.56,
  "predictions": {
    "15min": {
      "timestamp": "2026-04-15T05:19:30.888420+00:00",
      "price": 2336.7289867596046,
      "change_pct": -0.0417509155515915,
      "confidence_band": 0.43,
      "models": {
        "linear": 2336.0171225922595,
        "polynomial": 2336.1090498454287,
        "random_forest": 2336.8654458333335,
        "boosted": 2336.966274815386
      },
      "boosted_metrics": {
        "rmse": 1.6013,
        "directional_accuracy": 44.23,
        "train_size": 487,
        "test_size": 105,
        "models": [
          "lgb",
          "xgb"
        ],
        "feature_importance": {
          "close": 401.0,
          "volume": 139.0,
          "RSI": 121.0,
          "MACD": 143.0,
          "bb_position": 115.0,
          "obv": 232.0,
          "stoch_rsi": 97.0,
          "vwap_distance": 128.0,
          "atr_14": 161.0,
          "gas_price": 0.0,
          "fear_greed": 0.0
        }
      },
      "weights": {
        "lightgbm_xgboost": 0.75,
        "linear": 0.25,
        "polynomial": 0.0,
        "ml_features": 0.0
      },
      "weight_source": "boosted_ensemble"
    },
    "30min": {
      "timestamp": "2026-04-15T05:34:30.888420+00:00",
      "price": 2337.051732259154,
      "change_pct": -0.0279448322541072,
      "confidence_band": 0.24,
      "models": {
        "linear": 2337.308104590459,
        "polynomial": 2337.4597140999695,
        "random_forest": 2336.8654458333335,
        "boosted": 2336.966274815386
      },
      "boosted_metrics": {
        "rmse": 1.6013,
        "directional_accuracy": 44.23,
        "train_size": 487,
        "test_size": 105,
        "models": [
          "lgb",
          "xgb"
        ],
        "feature_importance": {
          "close": 401.0,
          "volume": 139.0,
          "RSI": 121.0,
          "MACD": 143.0,
          "bb_position": 115.0,
          "obv": 232.0,
          "stoch_rsi": 97.0,
          "vwap_distance": 128.0,
          "atr_14": 161.0,
          "gas_price": 0.0,
          "fear_greed": 0.0
        }
      },
      "weights": {
        "lightgbm_xgboost": 0.75,
        "linear": 0.25,
        "polynomial": 0.0,
        "ml_features": 0.0
      },
      "weight_source": "boosted_ensemble"
    },
    "60min": {
      "timestamp": "2026-04-15T06:04:30.888420+00:00",
      "price": 2337.6972232582543,
      "change_pct": -0.0003326656590802352,
      "confidence_band": 1.57,
      "models": {
        "linear": 2339.890068586859,
        "polynomial": 2340.198344019264,
        "random_forest": 2336.8654458333335,
        "boosted": 2336.966274815386
      },
      "boosted_metrics": {
        "rmse": 1.6013,
        "directional_accuracy": 44.23,
        "train_size": 487,
        "test_size": 105,
        "models": [
          "lgb",
          "xgb"
        ],
        "feature_importance": {
          "close": 401.0,
          "volume": 139.0,
          "RSI": 121.0,
          "MACD": 143.0,
          "bb_position": 115.0,
          "obv": 232.0,
          "stoch_rsi": 97.0,
          "vwap_distance": 128.0,
          "atr_14": 161.0,
          "gas_price": 0.0,
          "fear_greed": 0.0
        }
      },
      "weights": {
        "lightgbm_xgboost": 0.75,
        "linear": 0.25,
        "polynomial": 0.0,
        "ml_features": 0.0
      },
      "weight_source": "boosted_ensemble"
    },
    "120min": {
      "timestamp": "2026-04-15T07:04:30.888420+00:00",
      "price": 2338.988205256454,
      "change_pct": 0.054891667530934794,
      "confidence_band": 4.27,
      "models": {
        "linear": 2345.0539965796584,
        "polynomial": 2345.824809498705,
        "random_forest": 2336.8654458333335,
        "boosted": 2336.966274815386
      },
      "boosted_metrics": {
        "rmse": 1.6013,
        "directional_accuracy": 44.23,
        "train_size": 487,
        "test_size": 105,
        "models": [
          "lgb",
          "xgb"
        ],
        "feature_importance": {
          "close": 401.0,
          "volume": 139.0,
          "RSI": 121.0,
          "MACD": 143.0,
          "bb_position": 115.0,
          "obv": 232.0,
          "stoch_rsi": 97.0,
          "vwap_distance": 128.0,
          "atr_14": 161.0,
          "gas_price": 0.0,
          "fear_greed": 0.0
        }
      },
      "weights": {
        "lightgbm_xgboost": 0.75,
        "linear": 0.25,
        "polynomial": 0.0,
        "ml_features": 0.0
      },
      "weight_source": "boosted_ensemble"
    }
  },
  "market_condition": null,
  "rl_enabled": false,
  "accuracy_summary": null,
  "onchain_data": {
    "gas": {
      "safe_gas_gwei": null,
      "propose_gas_gwei": null,
      "fast_gas_gwei": null,
      "label": "LOW"
    },
    "uniswap_v3_pool": {
      "token0_price": null,
      "token1_price": null,
      "liquidity": null,
      "tick": null,
      "tvl_usd": null,
      "volume_24h_usd": null,
      "fees_24h_usd": null,
      "hour_data": []
    },
    "fear_greed": {
      "value": 23,
      "label": "Extreme Fear",
      "history": [
        {
          "value": 23,
          "label": "Extreme Fear"
        },
        {
          "value": 21,
          "label": "Extreme Fear"
        },
        {
          "value": 12,
          "label": "Extreme Fear"
        },
        {
          "value": 16,
          "label": "Extreme Fear"
        },
        {
          "value": 15,
          "label": "Extreme Fear"
        },
        {
          "value": 16,
          "label": "Extreme Fear"
        },
        {
          "value": 14,
          "label": "Extreme Fear"
        }
      ]
    },
    "eth_supply": {
      "eth_burned_all_time": null,
      "supply_change": null
    },
    "onchain_momentum": "BULLISH",
    "fetched_at": "2026-04-15T05:04:30.888380Z"
  },
  "model_scores": {
    "linear": 0.5,
    "polynomial": 0.7,
    "ml_features": 0.9
  },
  "model_weights": {
    "linear": 0.25,
    "polynomial": 0.35,
    "ml_features": 0.4
  },
  "trend_analysis": {
    "trend": "NEUTRAL",
    "rsi": 50.0,
    "rsi_signal": "NEUTRAL",
    "macd": 0.0,
    "macd_signal": "NEUTRAL",
    "bb_position": "MIDDLE",
    "current_price": 2336.56,
    "sma_20": 2336.56,
    "bb_upper": 2383.2912,
    "bb_lower": 2289.8288
  }
}