{
  "spot": {},
  "regime": {
    "regime": "MEDIUM",
    "vol_1h_pct": 42.96,
    "vol_4h_pct": 56.72,
    "vol_24h_pct": 67.45,
    "primary_vol_pct": 67.45,
    "atr": 0.77,
    "timestamp": "2026-06-07T18:37:31.036031"
  },
  "lp": {
    "regime": "MEDIUM",
    "range_pct": 10.0,
    "lower_price": 1470.75,
    "upper_price": 1797.59,
    "recommendation": "ADD_LIQUIDITY",
    "il_at_boundary_pct": -0.11,
    "fee_apy": 140.6,
    "net_expected_return_pct": 140.5,
    "tvl_used": 1946.6,
    "current_price": 1634.17,
    "timestamp": "2026-06-07T18:37:31.036193"
  },
  "strength": {
    "score": 50,
    "signal": "WAIT",
    "raw_signal": "WAIT",
    "regime_filtered": false,
    "components": {
      "rsi": 10,
      "macd": 5,
      "bb": 10,
      "volume": 10,
      "regime": 15
    },
    "sushiswap_context": "ETH/USDC \u2014 hold current positions; monitor funding rate"
  }
}