{
  "spot": {
    "price": 1820.7,
    "change_24h": -0.1631226400129738,
    "volume_24h": 6452674289.695226
  },
  "regime": {
    "regime": "LOW",
    "vol_1h_pct": 22.48,
    "vol_4h_pct": 32.09,
    "vol_24h_pct": 32.3,
    "primary_vol_pct": 32.3,
    "atr": 0.29,
    "timestamp": "2026-07-12T19:12:19.526541"
  },
  "lp": {
    "regime": "LOW",
    "range_pct": 5.0,
    "lower_price": 1729.66,
    "upper_price": 1911.74,
    "recommendation": "ADD_LIQUIDITY",
    "il_at_boundary_pct": -0.03,
    "fee_apy": 257.9,
    "net_expected_return_pct": 257.9,
    "tvl_used": 2123.2,
    "current_price": 1820.7,
    "timestamp": "2026-07-12T19:12:19.526565"
  },
  "strength": {
    "score": 45,
    "signal": "WAIT",
    "raw_signal": "WAIT",
    "regime_filtered": false,
    "components": {
      "rsi": 10,
      "macd": 5,
      "bb": 10,
      "volume": 10,
      "regime": 10
    },
    "sushiswap_context": "ETH/USDC \u2014 hold current positions; monitor funding rate"
  }
}