{
  "spot": {},
  "regime": {
    "regime": "HIGH",
    "vol_1h_pct": 95.16,
    "vol_4h_pct": 80.93,
    "vol_24h_pct": 84.18,
    "primary_vol_pct": 84.18,
    "atr": 4.15,
    "timestamp": "2026-03-17T04:42:12.012468"
  },
  "lp": {
    "regime": "HIGH",
    "range_pct": 20.0,
    "lower_price": 1844.41,
    "upper_price": 2766.61,
    "recommendation": "HOLD",
    "il_at_boundary_pct": -0.41,
    "fee_apy": 59.6,
    "net_expected_return_pct": 59.2,
    "tvl_used": 2294.9,
    "current_price": 2305.51,
    "timestamp": "2026-03-17T04:42:12.012632"
  },
  "strength": {
    "score": 43,
    "signal": "WAIT",
    "raw_signal": "WAIT",
    "regime_filtered": false,
    "components": {
      "rsi": 10,
      "macd": 5,
      "bb": 10,
      "volume": 10,
      "regime": 8
    },
    "sushiswap_context": "ETH/USDC \u2014 hold current positions; monitor funding rate"
  }
}