{
  "spot": {
    "price": 1743.03,
    "change_24h": 1.1196921342127288,
    "volume_24h": 15322740168.582603
  },
  "regime": {
    "regime": "MEDIUM",
    "vol_1h_pct": 36.99,
    "vol_4h_pct": 52.92,
    "vol_24h_pct": 52.03,
    "primary_vol_pct": 52.03,
    "atr": 0.59,
    "timestamp": "2026-06-22T18:28:23.082171"
  },
  "lp": {
    "regime": "MEDIUM",
    "range_pct": 10.0,
    "lower_price": 1568.73,
    "upper_price": 1917.33,
    "recommendation": "ADD_LIQUIDITY",
    "il_at_boundary_pct": -0.11,
    "fee_apy": 124.1,
    "net_expected_return_pct": 124.0,
    "tvl_used": 2205.4,
    "current_price": 1743.03,
    "timestamp": "2026-06-22T18:28:23.082194"
  },
  "strength": {
    "score": 50,
    "signal": "WAIT",
    "raw_signal": "WAIT",
    "regime_filtered": false,
    "components": {
      "rsi": 10,
      "macd": 5,
      "bb": 10,
      "volume": 10,
      "regime": 15
    },
    "sushiswap_context": "ETH/USDC \u2014 hold current positions; monitor funding rate"
  }
}