{
  "spot": {
    "price": 1683.62,
    "change_24h": 0.79678246823091,
    "volume_24h": 7167590808.450776
  },
  "regime": {
    "regime": "LOW",
    "vol_1h_pct": 24.54,
    "vol_4h_pct": 25.0,
    "vol_24h_pct": 22.62,
    "primary_vol_pct": 22.62,
    "atr": 0.63,
    "timestamp": "2026-06-13T15:40:18.494568"
  },
  "lp": {
    "regime": "LOW",
    "range_pct": 5.0,
    "lower_price": 1599.44,
    "upper_price": 1767.8,
    "recommendation": "ADD_LIQUIDITY",
    "il_at_boundary_pct": -0.03,
    "fee_apy": 286.3,
    "net_expected_return_pct": 286.3,
    "tvl_used": 1912.5,
    "current_price": 1683.62,
    "timestamp": "2026-06-13T15:40:18.494589"
  },
  "strength": {
    "score": 45,
    "signal": "WAIT",
    "raw_signal": "WAIT",
    "regime_filtered": false,
    "components": {
      "rsi": 10,
      "macd": 5,
      "bb": 10,
      "volume": 10,
      "regime": 10
    },
    "sushiswap_context": "ETH/USDC \u2014 hold current positions; monitor funding rate"
  }
}