{
  "spot": {},
  "regime": {
    "regime": "HIGH",
    "vol_1h_pct": 75.05,
    "vol_4h_pct": 85.91,
    "vol_24h_pct": 90.01,
    "primary_vol_pct": 90.01,
    "atr": 2.53,
    "timestamp": "2026-03-05T19:33:02.134357"
  },
  "lp": {
    "regime": "HIGH",
    "range_pct": 20.0,
    "lower_price": 1661.02,
    "upper_price": 2491.52,
    "recommendation": "HOLD",
    "il_at_boundary_pct": -0.41,
    "fee_apy": 62.9,
    "net_expected_return_pct": 62.5,
    "tvl_used": 2177.3,
    "current_price": 2076.27,
    "timestamp": "2026-03-05T19:33:02.134541"
  },
  "strength": {
    "score": 43,
    "signal": "WAIT",
    "raw_signal": "WAIT",
    "regime_filtered": false,
    "components": {
      "rsi": 10,
      "macd": 5,
      "bb": 10,
      "volume": 10,
      "regime": 8
    },
    "sushiswap_context": "ETH/USDC \u2014 hold current positions; monitor funding rate"
  }
}