{
  "spot": {
    "price": 2367.63,
    "change_24h": 2.216767491087242,
    "volume_24h": 9067001273.736399
  },
  "regime": {
    "regime": "LOW",
    "vol_1h_pct": 24.49,
    "vol_4h_pct": 38.23,
    "vol_24h_pct": 30.91,
    "primary_vol_pct": 30.91,
    "atr": 0.77,
    "timestamp": "2026-04-26T21:17:58.049004"
  },
  "lp": {
    "regime": "LOW",
    "range_pct": 5.0,
    "lower_price": 2249.25,
    "upper_price": 2486.01,
    "recommendation": "ADD_LIQUIDITY",
    "il_at_boundary_pct": -0.03,
    "fee_apy": 226.5,
    "net_expected_return_pct": 226.5,
    "tvl_used": 2417.4,
    "current_price": 2367.63,
    "timestamp": "2026-04-26T21:17:58.049025"
  },
  "strength": {
    "score": 45,
    "signal": "WAIT",
    "raw_signal": "WAIT",
    "regime_filtered": false,
    "components": {
      "rsi": 10,
      "macd": 5,
      "bb": 10,
      "volume": 10,
      "regime": 10
    },
    "sushiswap_context": "ETH/USDC \u2014 hold current positions; monitor funding rate"
  }
}