{
  "spot": {
    "price": 2261.05,
    "change_24h": -2.0279268344402803,
    "volume_24h": 15228990330.123713
  },
  "regime": {
    "regime": "LOW",
    "vol_1h_pct": 37.4,
    "vol_4h_pct": 28.96,
    "vol_24h_pct": 30.77,
    "primary_vol_pct": 30.77,
    "atr": 1.06,
    "timestamp": "2026-05-14T10:55:34.417616"
  },
  "lp": {
    "regime": "LOW",
    "range_pct": 5.0,
    "lower_price": 2148.0,
    "upper_price": 2374.1,
    "recommendation": "ADD_LIQUIDITY",
    "il_at_boundary_pct": -0.03,
    "fee_apy": 2737.5,
    "net_expected_return_pct": 2737.5,
    "tvl_used": 200.0,
    "current_price": 2261.05,
    "timestamp": "2026-05-14T10:55:34.417639"
  },
  "strength": {
    "score": 45,
    "signal": "WAIT",
    "raw_signal": "WAIT",
    "regime_filtered": false,
    "components": {
      "rsi": 10,
      "macd": 5,
      "bb": 10,
      "volume": 10,
      "regime": 10
    },
    "sushiswap_context": "ETH/USDC \u2014 hold current positions; monitor funding rate"
  }
}