{
  "spot": {
    "price": 1741.29,
    "change_24h": -2.0034959484301127,
    "volume_24h": 10361476082.868988
  },
  "regime": {
    "regime": "MEDIUM",
    "vol_1h_pct": 27.79,
    "vol_4h_pct": 35.35,
    "vol_24h_pct": 54.29,
    "primary_vol_pct": 54.29,
    "atr": 0.72,
    "timestamp": "2026-07-08T23:13:52.515713"
  },
  "lp": {
    "regime": "MEDIUM",
    "range_pct": 10.0,
    "lower_price": 1567.16,
    "upper_price": 1915.42,
    "recommendation": "ADD_LIQUIDITY",
    "il_at_boundary_pct": -0.11,
    "fee_apy": 130.0,
    "net_expected_return_pct": 129.9,
    "tvl_used": 2105.5,
    "current_price": 1741.29,
    "timestamp": "2026-07-08T23:13:52.515740"
  },
  "strength": {
    "score": 50,
    "signal": "WAIT",
    "raw_signal": "WAIT",
    "regime_filtered": false,
    "components": {
      "rsi": 10,
      "macd": 5,
      "bb": 10,
      "volume": 10,
      "regime": 15
    },
    "sushiswap_context": "ETH/USDC \u2014 hold current positions; monitor funding rate"
  }
}