{
  "generated_at": "2026-01-21T20:06:56.628236",
  "current_price": 3038.72,
  "last_data_timestamp": "2026-01-21T20:06:00",
  "trend_analysis": {
    "trend": "BEARISH",
    "rsi": 45.753424657534126,
    "rsi_signal": "NEUTRAL",
    "macd": 6.993658323939599,
    "macd_signal": "BEARISH",
    "bb_position": "MIDDLE",
    "current_price": 3038.72,
    "sma_20": 3046.6655,
    "bb_upper": 3062.1727770352823,
    "bb_lower": 3031.158222964718
  },
  "model_scores": {
    "linear": 0.8291000646164978,
    "polynomial": 0.8904970033058875,
    "ml_features": 0.9981881120071515
  },
  "model_weights": {
    "linear": 0.3050646058192111,
    "polynomial": 0.32765540480612054,
    "ml_features": 0.36727998937466844
  },
  "ensemble_r2": 0.911319759665649,
  "predictions": {
    "15m": {
      "price": 3083.977655668804,
      "change_pct": 1.4893657746947397,
      "timestamp": "2026-01-21T20:21:00"
    },
    "30m": {
      "price": 3114.4597107749933,
      "change_pct": 2.492487322787018,
      "timestamp": "2026-01-21T20:36:00"
    },
    "60m": {
      "price": 3183.8086128228824,
      "change_pct": 4.774662121646034,
      "timestamp": "2026-01-21T21:06:00"
    },
    "120m": {
      "price": 3356.0455842607107,
      "change_pct": 10.442738530062368,
      "timestamp": "2026-01-21T22:06:00"
    }
  }
}